SpatialSCvis.py
SpatialSCvis-0.0.3.dist-info/LICENSE
SpatialSCvis-0.0.3.dist-info/METADATA
SpatialSCvis-0.0.3.dist-info/WHEEL
SpatialSCvis-0.0.3.dist-info/top_level.txt
SpatialSCvis-0.0.3.dist-info/RECORD
