Metadata-Version: 2.1
Name: SpatialSCvis
Version: 0.0.3
Summary: A package to enable spatial visualization for single-cell data
Home-page: https://github.com/interactivereport/SpatialSC_vis
Author: Wanli Wang
Author-email: wendywangjk@gmail.com
License: MIT
Classifier: Programming Language :: Python :: 3
Classifier: License :: OSI Approved :: MIT License
Classifier: Operating System :: OS Independent
License-File: LICENSE
Requires-Dist: setuptools (>=61.0)
Requires-Dist: numpy (==1.20.0)
Requires-Dist: scanpy (==1.8.2)
Requires-Dist: pandas (==1.4.2)
